pyrob/__init__.py
pyrob/cli.py
pyrob/commands/__init__.py
pyrob/commands/init.py
pyrob/commands/install.py
pyrob/commands/run.py
pyrob/commands/uninstall.py
pyrob/config/__init__.py
pyrob/config/vars.py
pyrob/utils/__init__.py
pyrob/utils/git.py
pyrob/utils/meta.py
pyrob/utils/pip.py
pyrob-0.6.1.dist-info/LICENSE
pyrob-0.6.1.dist-info/METADATA
pyrob-0.6.1.dist-info/WHEEL
pyrob-0.6.1.dist-info/entry_points.txt
pyrob-0.6.1.dist-info/top_level.txt
pyrob-0.6.1.dist-info/RECORD
