Metadata-Version: 2.1
Name: pyrob
Version: 0.6.1
Summary: A CLI to manage dependencies in a Python project
Author-email: Robert Adams <r0b4dams@gmail.com>
License: MIT License
Project-URL: Homepage, https://github.com/r0b4dams/pyrob
Project-URL: Issues, https://github.com/r0b4dams/pyrob/issues
Project-URL: Repository, https://github.com/r0b4dams/pyrob.git
Requires-Python: >=3.8
License-File: LICENSE
